cnlab/__init__.py
cnlab/there.py
cnlab-0.0.1.dist-info/METADATA
cnlab-0.0.1.dist-info/WHEEL
cnlab-0.0.1.dist-info/top_level.txt
cnlab-0.0.1.dist-info/RECORD
