Metadata-Version: 2.1
Name: cnlab
Version: 0.0.1
Summary: For creating nothing
Author: Oh Please!,
Author-email: amazinggorillaxo@gmail.com
Classifier: Programming Language :: Python :: 3
Classifier: Operating System :: OS Independent
